aws_eden_cli/__init__.py
aws_eden_cli/__main__.py
aws_eden_cli/cmdline.py
aws_eden_cli/consts.py
aws_eden_cli/dynamodb.py
aws_eden_cli/utils.py
aws_eden_cli-0.1.5.data/scripts/eden
aws_eden_cli-0.1.5.dist-info/LICENSE
aws_eden_cli-0.1.5.dist-info/METADATA
aws_eden_cli-0.1.5.dist-info/WHEEL
aws_eden_cli-0.1.5.dist-info/top_level.txt
aws_eden_cli-0.1.5.dist-info/zip-safe
aws_eden_cli-0.1.5.dist-info/RECORD
