Metadata-Version: 2.1
Name: aws-eden-cli
Version: 0.1.5
Summary: ECS Dynamic Environment Manager (eden) CLI
Home-page: https://github.com/baikonur-oss/aws-eden-cli
Author: Tamirlan Torgayev
Author-email: torgayev@me.com
License: MIT
Project-URL: Source Code, https://github.com/baikonur-oss/aws-eden-cli
Platform: UNKNOWN
Classifier: Development Status :: 4 - Beta
Classifier: Intended Audience :: Developers
Classifier: License :: OSI Approved :: MIT License
Classifier: Operating System :: OS Independent
Classifier: Programming Language :: Python :: 3
Requires-Dist: aws-eden-core (==0.1.2)
Requires-Dist: botocore
Requires-Dist: boto3
